[
    {
        "kanji": "難易",
        "kanaRead": "なんい",
        "engRead": "difficulty"
    },
    {
        "kanji": "吹き流し",
        "kanaRead": "ふきながし",
        "engRead": "streamer"
    },
    {
        "kanji": "恵方巻",
        "kanaRead": "えほうまき",
        "engRead": "ehōmaki"
    },
    {
        "kanji": "老害",
        "kanaRead": "ろうがい",
        "engRead": "problems caused by the elderly (esp. gerontocracy, and elderly people's control over the young)"
    },
    {
        "kanji": "快晴",
        "kanaRead": "かいせい",
        "engRead": "clear weather"
    },
    {
        "kanji": "模様",
        "kanaRead": "もよう",
        "engRead": "pattern"
    },
    {
        "kanji": "家紋",
        "kanaRead": "かもん",
        "engRead": "family crest"
    },
    {
        "kanji": "指紋",
        "kanaRead": "しもん",
        "engRead": "fingerprint"
    },
    {
        "kanji": "絵馬",
        "kanaRead": "えま",
        "engRead": "votive picture (originally of horse)"
    },
    {
        "kanji": "友チョコ",
        "kanaRead": "ともチョコ",
        "engRead": "chocolate given to a friend (on Valentine's day)"
    },
    {
        "kanji": "蕾",
        "kanaRead": "つぼみ",
        "engRead": "(flower) bud"
    },
    {
        "kanji": "二枚目",
        "kanaRead": "にまいめ",
        "engRead": "handsome man"
    },
    {
        "kanji": "金継ぎ",
        "kanaRead": "きんつぎ",
        "engRead": "repairing pottery with a lacquer mixed with gold, silver, etc."
    },
    {
        "kanji": "梅雨",
        "kanaRead": "つゆ",
        "engRead": "rainy season (in Japan usu. from early June to mid-July)"
    },
    {
        "kanji": "木漏れ日",
        "kanaRead": "こもれび",
        "engRead": "sunlight filtering through trees"
    },
    {
        "kanji": "座礁",
        "kanaRead": "ざしょう",
        "engRead": "running aground"
    },
    {
        "kanji": "沈丁花",
        "kanaRead": "じんちょうげ",
        "engRead": "winter daphne (Daphne odora)"
    },
    {
        "kanji": "金木犀",
        "kanaRead": "きんもくせい",
        "engRead": "fragrant olive (Osmanthus fragrans var. aurantiacus)"
    },
    {
        "kanji": "嵐",
        "kanaRead": "あらし",
        "engRead": "storm"
    },
    {
        "kanji": "千羽鶴",
        "kanaRead": "せんばづる",
        "engRead": "(string of) many (traditionally 1000) paper cranes"
    },
    {
        "kanji": "業界用語",
        "kanaRead": "ぎょうかいようご",
        "engRead": "industry terminology"
    },
    {
        "kanji": "行方不明",
        "kanaRead": "ゆくえふめい",
        "engRead": "missing"
    },
    {
        "kanji": "凛々しい",
        "kanaRead": "りりしい",
        "engRead": "gallant"
    },
    {
        "kanji": "炉端焼き",
        "kanaRead": "ろばたやき",
        "engRead": "food cooked on a grill in front of customers"
    },
    {
        "kanji": "余裕綽々",
        "kanaRead": "よゆうしゃくしゃく",
        "engRead": "calm and collected"
    },
    {
        "kanji": "鼬ごっこ",
        "kanaRead": "いたちごっこ",
        "engRead": "going round in circles"
    },
    {
        "kanji": "四字熟語",
        "kanaRead": "よじじゅくご",
        "engRead": "four-character compound word (esp. idiomatic)"
    },
    {
        "kanji": "散策",
        "kanaRead": "さんさく",
        "engRead": "walking"
    },
    {
        "kanji": "閉会式",
        "kanaRead": "へいかいしき",
        "engRead": "closing ceremony"
    },
    {
        "kanji": "開運",
        "kanaRead": "かいうん",
        "engRead": "better fortune"
    },
    {
        "kanji": "運勢",
        "kanaRead": "うんせい",
        "engRead": "fortune"
    },
    {
        "kanji": "夕暮れ",
        "kanaRead": "ゆうぐれ",
        "engRead": "evening"
    },
    {
        "kanji": "お守り",
        "kanaRead": "おまもり",
        "engRead": "charm"
    },
    {
        "kanji": "不良品",
        "kanaRead": "ふりょうひん",
        "engRead": "inferior goods"
    }
]